peasant/__init__.py
peasant/server.py
peasant/client/__init__.py
peasant/client/protocol.py
peasant/client/transport.py
peasant/client/transport_requests.py
peasant/client/transport_tornado.py
peasant/security/__init__.py
peasant/security/ec.py
peasant/security/jwk.py
peasant/security/keyring.py
peasant/security/rsa.py
tests/__init__.py
tests/runtests.py
tests/transport_requests_test.py
tests/transport_test.py
tests/transport_tornado_test.py
peasant-0.7.4.dist-info/LICENSE
peasant-0.7.4.dist-info/METADATA
peasant-0.7.4.dist-info/WHEEL
peasant-0.7.4.dist-info/top_level.txt
peasant-0.7.4.dist-info/RECORD
