Metadata-Version: 2.1
Name: peasant
Version: 0.7.4
Summary: Peasant helps you to build APIs
Home-page: https://github.com/candango/peasant
Author: Flavio Garcia
Author-email: piraz@candango.org
License: Apache License V2.0
Classifier: Development Status :: 1 - Planning
Classifier: License :: OSI Approved :: Apache Software License
Classifier: Environment :: Console
Classifier: Environment :: Web Environment
Classifier: Intended Audience :: Developers
Classifier: Intended Audience :: System Administrators
Classifier: Programming Language :: Python :: 3
Classifier: Programming Language :: Python :: 3.8
Classifier: Programming Language :: Python :: 3.9
Classifier: Programming Language :: Python :: 3.10
Classifier: Programming Language :: Python :: 3.11
Classifier: Programming Language :: Python :: 3.12
Classifier: Programming Language :: Python :: 3 :: Only
Classifier: Topic :: Software Development :: Libraries :: Application Frameworks
Requires-Python: >= 3.8
License-File: LICENSE
Requires-Dist: cartola >=0.18
Requires-Dist: cryptography ==42.0.8
Provides-Extra: all
Requires-Dist: cartola >=0.18 ; extra == 'all'
Requires-Dist: cryptography ==42.0.8 ; extra == 'all'
Requires-Dist: requests ==2.32.3 ; extra == 'all'
Requires-Dist: tornado >=6.4.1 ; extra == 'all'
Provides-Extra: requests
Requires-Dist: requests ==2.32.3 ; extra == 'requests'
Provides-Extra: tornado
Requires-Dist: tornado >=6.4.1 ; extra == 'tornado'
